concurrent_collections/__init__.py
concurrent_collections/__init__.pyi
concurrent_collections/concurrent_bag.py
concurrent_collections/concurrent_deque.py
concurrent_collections/concurrent_dict.py
concurrent_collections-2.1.0.dist-info/licenses/LICENSE
concurrent_collections-2.1.0.dist-info/METADATA
concurrent_collections-2.1.0.dist-info/WHEEL
concurrent_collections-2.1.0.dist-info/top_level.txt
concurrent_collections-2.1.0.dist-info/RECORD
