Metadata-Version: 2.4
Name: concurrent_collections
Version: 2.1.0
Summary: A brief description of concurrent-collections
Author-email: Alessio Lombardi <work@alelom.com>
Project-URL: Homepage, https://github.com/alelom/python-concurrentCollections
Requires-Python: >=3.6
License-File: LICENSE
Dynamic: license-file
